MANIFEST.in
README.txt
setup.py
docs/HISTORY.txt
docs/INSTALL.txt
docs/LICENSE.GPL
docs/LICENSE.txt
src/customer/__init__.py
src/customer.mlscrcom.egg-info/PKG-INFO
src/customer.mlscrcom.egg-info/SOURCES.txt
src/customer.mlscrcom.egg-info/dependency_links.txt
src/customer.mlscrcom.egg-info/entry_points.txt
src/customer.mlscrcom.egg-info/namespace_packages.txt
src/customer.mlscrcom.egg-info/not-zip-safe
src/customer.mlscrcom.egg-info/requires.txt
src/customer.mlscrcom.egg-info/top_level.txt
src/customer/mlscrcom/__init__.py
src/customer/mlscrcom/configure.zcml
src/customer/mlscrcom/i18n.py
src/customer/mlscrcom/interfaces.py
src/customer/mlscrcom/migration.py
src/customer/mlscrcom/profiles.zcml
src/customer/mlscrcom/setuphandlers.py
src/customer/mlscrcom/testing.py
src/customer/mlscrcom/browser/__init__.py
src/customer/mlscrcom/browser/configure.zcml
src/customer/mlscrcom/browser/controlpanel.py
src/customer/mlscrcom/browser/frontpage.py
src/customer/mlscrcom/browser/interfaces.py
src/customer/mlscrcom/browser/utils.py
src/customer/mlscrcom/browser/viewlets.py
src/customer/mlscrcom/browser/images/map.png
src/customer/mlscrcom/browser/images/mapAlajuela.png
src/customer/mlscrcom/browser/images/mapCartago.png
src/customer/mlscrcom/browser/images/mapGuanacaste.png
src/customer/mlscrcom/browser/images/mapHeredia.png
src/customer/mlscrcom/browser/images/mapLimon.png
src/customer/mlscrcom/browser/images/mapPuntarenas.png
src/customer/mlscrcom/browser/images/mapSanJose.png
src/customer/mlscrcom/browser/images/search-steps.jpg
src/customer/mlscrcom/browser/templates/frontpage.pt
src/customer/mlscrcom/browser/templates/listing-quick-search-viewlet.pt
src/customer/mlscrcom/browser/templates/listing-search-viewlet.pt
src/customer/mlscrcom/browser/templates/listing_search_viewlet.pt
src/customer/mlscrcom/locales/customer.mlscrcom.pot
src/customer/mlscrcom/locales/de/LC_MESSAGES/customer.mlscrcom.po
src/customer/mlscrcom/locales/en/LC_MESSAGES/customer.mlscrcom.po
src/customer/mlscrcom/locales/es/LC_MESSAGES/customer.mlscrcom.po
src/customer/mlscrcom/locales/fr/LC_MESSAGES/customer.mlscrcom.po
src/customer/mlscrcom/locales/it/LC_MESSAGES/customer.mlscrcom.po
src/customer/mlscrcom/locales/ja/LC_MESSAGES/customer.mlscrcom.po
src/customer/mlscrcom/locales/ru/LC_MESSAGES/customer.mlscrcom.po
