Metadata-Version: 1.0
Name: customer.mlscrcom
Version: 0.2
Summary: mls-cr.com Theme & Policy Product.
Home-page: http://pypi.propertyshelf.com
Author: Thomas Massmann
Author-email: thomas@propertyshelf.com
License: GPL
Download-URL: http://pypi.python.org/pypi/customer.mlscrcom
Keywords: web zope plone theme
Platform: UNKNOWN
Classifier: Development Status :: 4 - Beta
Classifier: Environment :: Web Environment
Classifier: Framework :: Plone
Classifier: Intended Audience :: Other Audience
Classifier: License :: Other/Proprietary License
Classifier: Natural Language :: English
Classifier: Operating System :: OS Independent
Classifier: Programming Language :: Python
Classifier: Programming Language :: Zope
